starsol_otp/__init__.py
starsol_otp/otp.py
starsol_otp-1.0.1.dist-info/LICENSE
starsol_otp-1.0.1.dist-info/METADATA
starsol_otp-1.0.1.dist-info/WHEEL
starsol_otp-1.0.1.dist-info/top_level.txt
starsol_otp-1.0.1.dist-info/RECORD
